gradiochat/__init__.py
gradiochat/_modidx.py
gradiochat/app.py
gradiochat/config.py
gradiochat/gradio_configpresets.py
gradiochat/gradio_themebuilder.py
gradiochat/gradio_themes.py
gradiochat/ui.py
gradiochat/utils.py
gradiochat-0.4.2.dist-info/METADATA
gradiochat-0.4.2.dist-info/WHEEL
gradiochat-0.4.2.dist-info/entry_points.txt
gradiochat-0.4.2.dist-info/licenses/LICENSE
gradiochat-0.4.2.dist-info/RECORD
