Metadata-Version: 2.4
Name: gradiochat
Version: 0.4.2
Summary: App to easily create different Gradiochat apps with different context, system messages and gradio themes.
Project-URL: Homepage, https://github.com/Hopsakee/gradiochat
Project-URL: Documentation, https://hopsakee.github.io/gradiochat/
Author-email: Hopsakee <jdejong@posteo.nl>
License-Expression: Apache-2.0
License-File: LICENSE
Classifier: Programming Language :: Python :: 3
Requires-Python: >=3.10
Requires-Dist: fastcore>=1.7.29
Requires-Dist: gradio>=5.20.1
Requires-Dist: ollama>=0.4.7
Requires-Dist: openai>=1.65.4
Requires-Dist: pydantic>=2.10.6
Requires-Dist: python-dotenv>=1.0.1
Requires-Dist: requests>=2.32.3
Requires-Dist: together>=1.4.6
